[
  {
    "reporter": 20,
    "partner": 380,
    "trade_value_usd_thousands": 16.221,
    "quantity_tonnes": null
  },
  {
    "reporter": 36,
    "partner": 56,
    "trade_value_usd_thousands": 36.313,
    "quantity_tonnes": null
  },
  {
    "reporter": 36,
    "partner": 842,
    "trade_value_usd_thousands": 8.246,
    "quantity_tonnes": null
  },
  {
    "reporter": 40,
    "partner": 276,
    "trade_value_usd_thousands": 113.531,
    "quantity_tonnes": null
  },
  {
    "reporter": 40,
    "partner": 380,
    "trade_value_usd_thousands": 33.237,
    "quantity_tonnes": 0.001
  },
  {
    "reporter": 40,
    "partner": 528,
    "trade_value_usd_thousands": 0.149,
    "quantity_tonnes": null
  },
  {
    "reporter": 48,
    "partner": 344,
    "trade_value_usd_thousands": 4018.434,
    "quantity_tonnes": 0.008
  },
  {
    "reporter": 48,
    "partner": 784,
    "trade_value_usd_thousands": 123.026,
    "quantity_tonnes": null
  },
  {
    "reporter": 48,
    "partner": 842,
    "trade_value_usd_thousands": 798.172,
    "quantity_tonnes": 0.002
  },
  {
    "reporter": 56,
    "partner": 40,
    "trade_value_usd_thousands": 16.836,
    "quantity_tonnes": null
  },
  {
    "reporter": 56,
    "partner": 48,
    "trade_value_usd_thousands": 625.127,
    "quantity_tonnes": null
  },
  {
    "reporter": 56,
    "partner": 72,
    "trade_value_usd_thousands": 1970.708,
    "quantity_tonnes": 0.004
  },
  {
    "reporter": 56,
    "partner": 246,
    "trade_value_usd_thousands": 182.687,
    "quantity_tonnes": null
  },
  {
    "reporter": 56,
    "partner": 251,
    "trade_value_usd_thousands": 22672.166,
    "quantity_tonnes": 0.302
  },
  {
    "reporter": 56,
    "partner": 276,
    "trade_value_usd_thousands": 16.01,
    "quantity_tonnes": null
  },
  {
    "reporter": 56,
    "partner": 300,
    "trade_value_usd_thousands": 592.7,
    "quantity_tonnes": 0.038
  },
  {
    "reporter": 56,
    "partner": 352,
    "trade_value_usd_thousands": 1.375,
    "quantity_tonnes": 0.002
  },
  {
    "reporter": 56,
    "partner": 372,
    "trade_value_usd_thousands": 654.372,
    "quantity_tonnes": 0.004
  },
  {
    "reporter": 56,
    "partner": 380,
    "trade_value_usd_thousands": 30440.685,
    "quantity_tonnes": 0.148
  },
  {
    "reporter": 56,
    "partner": 440,
    "trade_value_usd_thousands": 0.652,
    "quantity_tonnes": null
  },
  {
    "reporter": 56,
    "partner": 442,
    "trade_value_usd_thousands": 93.464,
    "quantity_tonnes": 0.002
  },
  {
    "reporter": 56,
    "partner": 470,
    "trade_value_usd_thousands": 0.71,
    "quantity_tonnes": 0.001
  },
  {
    "reporter": 56,
    "partner": 528,
    "trade_value_usd_thousands": 1.718,
    "quantity_tonnes": 0.014
  },
  {
    "reporter": 56,
    "partner": 682,
    "trade_value_usd_thousands": 45.236,
    "quantity_tonnes": null
  },
  {
    "reporter": 56,
    "partner": 724,
    "trade_value_usd_thousands": 2232.518,
    "quantity_tonnes": 0.065
  },
  {
    "reporter": 56,
    "partner": 784,
    "trade_value_usd_thousands": 1109.418,
    "quantity_tonnes": 0.01
  },
  {
    "reporter": 56,
    "partner": 788,
    "trade_value_usd_thousands": 198.985,
    "quantity_tonnes": 0.014
  },
  {
    "reporter": 72,
    "partner": 56,
    "trade_value_usd_thousands": 20774.5,
    "quantity_tonnes": 0.057
  },
  {
    "reporter": 72,
    "partner": 344,
    "trade_value_usd_thousands": 840.834,
    "quantity_tonnes": 0.006
  },
  {
    "reporter": 72,
    "partner": 376,
    "trade_value_usd_thousands": 26.0,
    "quantity_tonnes": null
  },
  {
    "reporter": 72,
    "partner": 784,
    "trade_value_usd_thousands": 5832.432,
    "quantity_tonnes": 0.011
  },
  {
    "reporter": 76,
    "partner": 56,
    "trade_value_usd_thousands": 17623.056,
    "quantity_tonnes": 0.018
  },
  {
    "reporter": 76,
    "partner": 376,
    "trade_value_usd_thousands": 112.497,
    "quantity_tonnes": null
  },
  {
    "reporter": 76,
    "partner": 784,
    "trade_value_usd_thousands": 142.656,
    "quantity_tonnes": null
  },
  {
    "reporter": 76,
    "partner": 842,
    "trade_value_usd_thousands": 138.769,
    "quantity_tonnes": null
  },
  {
    "reporter": 100,
    "partner": 300,
    "trade_value_usd_thousands": 43.353,
    "quantity_tonnes": null
  },
  {
    "reporter": 100,
    "partner": 528,
    "trade_value_usd_thousands": 0.023,
    "quantity_tonnes": null
  },
  {
    "reporter": 120,
    "partner": 276,
    "trade_value_usd_thousands": 11.078,
    "quantity_tonnes": null
  },
  {
    "reporter": 120,
    "partner": 784,
    "trade_value_usd_thousands": 17.563,
    "quantity_tonnes": null
  },
  {
    "reporter": 124,
    "partner": 36,
    "trade_value_usd_thousands": 23.292,
    "quantity_tonnes": null
  },
  {
    "reporter": 124,
    "partner": 56,
    "trade_value_usd_thousands": 363059.472,
    "quantity_tonnes": 0.622
  },
  {
    "reporter": 124,
    "partner": 72,
    "trade_value_usd_thousands": 239088.791,
    "quantity_tonnes": 0.831
  },
  {
    "reporter": 124,
    "partner": 276,
    "trade_value_usd_thousands": 24.182,
    "quantity_tonnes": null
  },
  {
    "reporter": 124,
    "partner": 344,
    "trade_value_usd_thousands": 73.642,
    "quantity_tonnes": null
  },
  {
    "reporter": 124,
    "partner": 699,
    "trade_value_usd_thousands": 128804.039,
    "quantity_tonnes": 0.458
  },
  {
    "reporter": 124,
    "partner": 757,
    "trade_value_usd_thousands": 13.306,
    "quantity_tonnes": null
  },
  {
    "reporter": 124,
    "partner": 826,
    "trade_value_usd_thousands": 6.135,
    "quantity_tonnes": null
  },
  {
    "reporter": 124,
    "partner": 842,
    "trade_value_usd_thousands": 5.529,
    "quantity_tonnes": null
  },
  {
    "reporter": 140,
    "partner": 56,
    "trade_value_usd_thousands": 218.19,
    "quantity_tonnes": 0.002
  },
  {
    "reporter": 140,
    "partner": 710,
    "trade_value_usd_thousands": 302.996,
    "quantity_tonnes": null
  },
  {
    "reporter": 140,
    "partner": 784,
    "trade_value_usd_thousands": 11762.815,
    "quantity_tonnes": null
  },
  {
    "reporter": 156,
    "partner": 344,
    "trade_value_usd_thousands": 82.0,
    "quantity_tonnes": null
  },
  {
    "reporter": 156,
    "partner": 784,
    "trade_value_usd_thousands": 155.994,
    "quantity_tonnes": null
  },
  {
    "reporter": 156,
    "partner": 788,
    "trade_value_usd_thousands": 42.103,
    "quantity_tonnes": 0.002
  },
  {
    "reporter": 156,
    "partner": 826,
    "trade_value_usd_thousands": 14.126,
    "quantity_tonnes": 0.001
  },
  {
    "reporter": 180,
    "partner": 784,
    "trade_value_usd_thousands": 78.079,
    "quantity_tonnes": null
  },
  {
    "reporter": 188,
    "partner": 558,
    "trade_value_usd_thousands": 0.002,
    "quantity_tonnes": null
  },
  {
    "reporter": 191,
    "partner": 528,
    "trade_value_usd_thousands": 0.004,
    "quantity_tonnes": null
  },
  {
    "reporter": 203,
    "partner": 528,
    "trade_value_usd_thousands": 0.682,
    "quantity_tonnes": null
  },
  {
    "reporter": 208,
    "partner": 528,
    "trade_value_usd_thousands": 0.439,
    "quantity_tonnes": null
  },
  {
    "reporter": 208,
    "partner": 826,
    "trade_value_usd_thousands": 7.282,
    "quantity_tonnes": 0.002
  },
  {
    "reporter": 214,
    "partner": 842,
    "trade_value_usd_thousands": 244.375,
    "quantity_tonnes": 0.011
  },
  {
    "reporter": 233,
    "partner": 528,
    "trade_value_usd_thousands": 0.005,
    "quantity_tonnes": null
  },
  {
    "reporter": 242,
    "partner": 36,
    "trade_value_usd_thousands": 19.839,
    "quantity_tonnes": null
  },
  {
    "reporter": 246,
    "partner": 528,
    "trade_value_usd_thousands": 0.055,
    "quantity_tonnes": null
  },
  {
    "reporter": 251,
    "partner": 56,
    "trade_value_usd_thousands": 21.298,
    "quantity_tonnes": 0.002
  },
  {
    "reporter": 251,
    "partner": 276,
    "trade_value_usd_thousands": 1.082,
    "quantity_tonnes": 0.002
  },
  {
    "reporter": 251,
    "partner": 380,
    "trade_value_usd_thousands": 569.08,
    "quantity_tonnes": 0.017
  },
  {
    "reporter": 251,
    "partner": 442,
    "trade_value_usd_thousands": 3.16,
    "quantity_tonnes": 0.002
  },
  {
    "reporter": 251,
    "partner": 528,
    "trade_value_usd_thousands": 0.868,
    "quantity_tonnes": null
  },
  {
    "reporter": 251,
    "partner": 724,
    "trade_value_usd_thousands": 0.335,
    "quantity_tonnes": 0.002
  },
  {
    "reporter": 251,
    "partner": 752,
    "trade_value_usd_thousands": 0.848,
    "quantity_tonnes": null
  },
  {
    "reporter": 251,
    "partner": 757,
    "trade_value_usd_thousands": 0.054,
    "quantity_tonnes": null
  },
  {
    "reporter": 251,
    "partner": 788,
    "trade_value_usd_thousands": 18.175,
    "quantity_tonnes": 0.001
  },
  {
    "reporter": 276,
    "partner": 40,
    "trade_value_usd_thousands": 99.203,
    "quantity_tonnes": null
  },
  {
    "reporter": 276,
    "partner": 56,
    "trade_value_usd_thousands": 73.278,
    "quantity_tonnes": null
  },
  {
    "reporter": 276,
    "partner": 246,
    "trade_value_usd_thousands": 23.439,
    "quantity_tonnes": null
  },
  {
    "reporter": 276,
    "partner": 300,
    "trade_value_usd_thousands": 239.988,
    "quantity_tonnes": 0.078
  },
  {
    "reporter": 276,
    "partner": 372,
    "trade_value_usd_thousands": 27.11,
    "quantity_tonnes": null
  },
  {
    "reporter": 276,
    "partner": 398,
    "trade_value_usd_thousands": 16.736,
    "quantity_tonnes": null
  },
  {
    "reporter": 276,
    "partner": 442,
    "trade_value_usd_thousands": 44.505,
    "quantity_tonnes": 0.001
  },
  {
    "reporter": 276,
    "partner": 528,
    "trade_value_usd_thousands": 36.793,
    "quantity_tonnes": null
  },
  {
    "reporter": 276,
    "partner": 705,
    "trade_value_usd_thousands": 2.378,
    "quantity_tonnes": null
  },
  {
    "reporter": 276,
    "partner": 757,
    "trade_value_usd_thousands": 0.359,
    "quantity_tonnes": null
  },
  {
    "reporter": 288,
    "partner": 784,
    "trade_value_usd_thousands": 64.178,
    "quantity_tonnes": null
  },
  {
    "reporter": 288,
    "partner": 842,
    "trade_value_usd_thousands": 20.001,
    "quantity_tonnes": null
  },
  {
    "reporter": 300,
    "partner": 528,
    "trade_value_usd_thousands": 0.054,
    "quantity_tonnes": null
  },
  {
    "reporter": 320,
    "partner": 340,
    "trade_value_usd_thousands": 0.684,
    "quantity_tonnes": null
  },
  {
    "reporter": 324,
    "partner": 56,
    "trade_value_usd_thousands": 227.436,
    "quantity_tonnes": 0.002
  },
  {
    "reporter": 324,
    "partner": 784,
    "trade_value_usd_thousands": 4143.803,
    "quantity_tonnes": null
  },
  {
    "reporter": 328,
    "partner": 56,
    "trade_value_usd_thousands": 2982.726,
    "quantity_tonnes": 0.009
  },
  {
    "reporter": 328,
    "partner": 699,
    "trade_value_usd_thousands": 477.189,
    "quantity_tonnes": 0.001
  },
  {
    "reporter": 328,
    "partner": 784,
    "trade_value_usd_thousands": 5147.822,
    "quantity_tonnes": null
  },
  {
    "reporter": 328,
    "partner": 842,
    "trade_value_usd_thousands": 578.746,
    "quantity_tonnes": 0.001
  },
  {
    "reporter": 344,
    "partner": 699,
    "trade_value_usd_thousands": 9.642,
    "quantity_tonnes": null
  },
  {
    "reporter": 344,
    "partner": 702,
    "trade_value_usd_thousands": 26.627,
    "quantity_tonnes": null
  },
  {
    "reporter": 344,
    "partner": 724,
    "trade_value_usd_thousands": 7.928,
    "quantity_tonnes": 0.001
  },
  {
    "reporter": 344,
    "partner": 842,
    "trade_value_usd_thousands": 9.046,
    "quantity_tonnes": null
  },
  {
    "reporter": 348,
    "partner": 276,
    "trade_value_usd_thousands": 0.013,
    "quantity_tonnes": null
  },
  {
    "reporter": 348,
    "partner": 528,
    "trade_value_usd_thousands": 0.034,
    "quantity_tonnes": null
  },
  {
    "reporter": 372,
    "partner": 208,
    "trade_value_usd_thousands": 3.805,
    "quantity_tonnes": null
  },
  {
    "reporter": 372,
    "partner": 251,
    "trade_value_usd_thousands": 0.324,
    "quantity_tonnes": 0.001
  },
  {
    "reporter": 372,
    "partner": 528,
    "trade_value_usd_thousands": 0.235,
    "quantity_tonnes": null
  },
  {
    "reporter": 372,
    "partner": 842,
    "trade_value_usd_thousands": 29.234,
    "quantity_tonnes": null
  },
  {
    "reporter": 376,
    "partner": 40,
    "trade_value_usd_thousands": 0.001,
    "quantity_tonnes": null
  },
  {
    "reporter": 376,
    "partner": 48,
    "trade_value_usd_thousands": 4613.849,
    "quantity_tonnes": null
  },
  {
    "reporter": 376,
    "partner": 124,
    "trade_value_usd_thousands": 39.209,
    "quantity_tonnes": null
  },
  {
    "reporter": 376,
    "partner": 251,
    "trade_value_usd_thousands": 0.001,
    "quantity_tonnes": null
  },
  {
    "reporter": 376,
    "partner": 442,
    "trade_value_usd_thousands": 3.603,
    "quantity_tonnes": null
  },
  {
    "reporter": 376,
    "partner": 554,
    "trade_value_usd_thousands": 1.0,
    "quantity_tonnes": null
  },
  {
    "reporter": 376,
    "partner": 724,
    "trade_value_usd_thousands": 2.987,
    "quantity_tonnes": 0.009
  },
  {
    "reporter": 380,
    "partner": 40,
    "trade_value_usd_thousands": 3.025,
    "quantity_tonnes": 0.002
  },
  {
    "reporter": 380,
    "partner": 56,
    "trade_value_usd_thousands": 8194.881,
    "quantity_tonnes": 0.031
  },
  {
    "reporter": 380,
    "partner": 100,
    "trade_value_usd_thousands": 12.388,
    "quantity_tonnes": 0.002
  },
  {
    "reporter": 380,
    "partner": 191,
    "trade_value_usd_thousands": 22.744,
    "quantity_tonnes": 0.003
  },
  {
    "reporter": 380,
    "partner": 208,
    "trade_value_usd_thousands": 16.811,
    "quantity_tonnes": 0.001
  },
  {
    "reporter": 380,
    "partner": 233,
    "trade_value_usd_thousands": 2.797,
    "quantity_tonnes": 0.001
  },
  {
    "reporter": 380,
    "partner": 251,
    "trade_value_usd_thousands": 413.78,
    "quantity_tonnes": 0.01
  },
  {
    "reporter": 380,
    "partner": 276,
    "trade_value_usd_thousands": 134.309,
    "quantity_tonnes": 0.011
  },
  {
    "reporter": 380,
    "partner": 300,
    "trade_value_usd_thousands": 118.863,
    "quantity_tonnes": 0.007
  },
  {
    "reporter": 380,
    "partner": 440,
    "trade_value_usd_thousands": 4.893,
    "quantity_tonnes": 0.002
  },
  {
    "reporter": 380,
    "partner": 470,
    "trade_value_usd_thousands": 103.369,
    "quantity_tonnes": 0.006
  },
  {
    "reporter": 380,
    "partner": 528,
    "trade_value_usd_thousands": 69.445,
    "quantity_tonnes": 0.012
  },
  {
    "reporter": 380,
    "partner": 620,
    "trade_value_usd_thousands": 1026.229,
    "quantity_tonnes": 0.009
  },
  {
    "reporter": 380,
    "partner": 703,
    "trade_value_usd_thousands": 0.973,
    "quantity_tonnes": 0.001
  },
  {
    "reporter": 380,
    "partner": 705,
    "trade_value_usd_thousands": 1.198,
    "quantity_tonnes": 0.003
  },
  {
    "reporter": 380,
    "partner": 724,
    "trade_value_usd_thousands": 759.258,
    "quantity_tonnes": 0.099
  },
  {
    "reporter": 380,
    "partner": 752,
    "trade_value_usd_thousands": 231.322,
    "quantity_tonnes": 0.011
  },
  {
    "reporter": 384,
    "partner": 56,
    "trade_value_usd_thousands": 159.667,
    "quantity_tonnes": 0.001
  },
  {
    "reporter": 392,
    "partner": 702,
    "trade_value_usd_thousands": 0.366,
    "quantity_tonnes": null
  },
  {
    "reporter": 428,
    "partner": 440,
    "trade_value_usd_thousands": 2.657,
    "quantity_tonnes": null
  },
  {
    "reporter": 428,
    "partner": 528,
    "trade_value_usd_thousands": 0.122,
    "quantity_tonnes": null
  },
  {
    "reporter": 430,
    "partner": 56,
    "trade_value_usd_thousands": 178.849,
    "quantity_tonnes": 0.001
  },
  {
    "reporter": 430,
    "partner": 376,
    "trade_value_usd_thousands": 355.0,
    "quantity_tonnes": null
  },
  {
    "reporter": 430,
    "partner": 842,
    "trade_value_usd_thousands": 26.592,
    "quantity_tonnes": null
  },
  {
    "reporter": 440,
    "partner": 528,
    "trade_value_usd_thousands": 0.07,
    "quantity_tonnes": null
  },
  {
    "reporter": 442,
    "partner": 528,
    "trade_value_usd_thousands": 0.032,
    "quantity_tonnes": null
  },
  {
    "reporter": 458,
    "partner": 702,
    "trade_value_usd_thousands": 22.924,
    "quantity_tonnes": null
  },
  {
    "reporter": 516,
    "partner": 372,
    "trade_value_usd_thousands": 3.533,
    "quantity_tonnes": null
  },
  {
    "reporter": 528,
    "partner": 56,
    "trade_value_usd_thousands": 0.777,
    "quantity_tonnes": null
  },
  {
    "reporter": 528,
    "partner": 251,
    "trade_value_usd_thousands": 1680.387,
    "quantity_tonnes": 0.132
  },
  {
    "reporter": 528,
    "partner": 470,
    "trade_value_usd_thousands": 11.574,
    "quantity_tonnes": 0.002
  },
  {
    "reporter": 528,
    "partner": 724,
    "trade_value_usd_thousands": 27.016,
    "quantity_tonnes": null
  },
  {
    "reporter": 528,
    "partner": 757,
    "trade_value_usd_thousands": 0.958,
    "quantity_tonnes": null
  },
  {
    "reporter": 566,
    "partner": 276,
    "trade_value_usd_thousands": 0.959,
    "quantity_tonnes": 0.002
  },
  {
    "reporter": 586,
    "partner": 764,
    "trade_value_usd_thousands": 12.083,
    "quantity_tonnes": 0.011
  },
  {
    "reporter": 586,
    "partner": 784,
    "trade_value_usd_thousands": 14.077,
    "quantity_tonnes": 0.015
  },
  {
    "reporter": 586,
    "partner": 842,
    "trade_value_usd_thousands": 3.635,
    "quantity_tonnes": 0.001
  },
  {
    "reporter": 616,
    "partner": 203,
    "trade_value_usd_thousands": 0.041,
    "quantity_tonnes": null
  },
  {
    "reporter": 616,
    "partner": 233,
    "trade_value_usd_thousands": 40.256,
    "quantity_tonnes": null
  },
  {
    "reporter": 616,
    "partner": 440,
    "trade_value_usd_thousands": 0.297,
    "quantity_tonnes": null
  },
  {
    "reporter": 616,
    "partner": 528,
    "trade_value_usd_thousands": 0.442,
    "quantity_tonnes": null
  },
  {
    "reporter": 620,
    "partner": 251,
    "trade_value_usd_thousands": 2.706,
    "quantity_tonnes": 0.001
  },
  {
    "reporter": 620,
    "partner": 528,
    "trade_value_usd_thousands": 0.191,
    "quantity_tonnes": null
  },
  {
    "reporter": 642,
    "partner": 528,
    "trade_value_usd_thousands": 0.144,
    "quantity_tonnes": null
  },
  {
    "reporter": 643,
    "partner": 398,
    "trade_value_usd_thousands": 1937.382,
    "quantity_tonnes": null
  },
  {
    "reporter": 646,
    "partner": 699,
    "trade_value_usd_thousands": 465.008,
    "quantity_tonnes": null
  },
  {
    "reporter": 699,
    "partner": 40,
    "trade_value_usd_thousands": 23.225,
    "quantity_tonnes": null
  },
  {
    "reporter": 699,
    "partner": 48,
    "trade_value_usd_thousands": 147.995,
    "quantity_tonnes": null
  },
  {
    "reporter": 699,
    "partner": 124,
    "trade_value_usd_thousands": 1.412,
    "quantity_tonnes": null
  },
  {
    "reporter": 699,
    "partner": 372,
    "trade_value_usd_thousands": 130.3,
    "quantity_tonnes": 0.004
  },
  {
    "reporter": 699,
    "partner": 392,
    "trade_value_usd_thousands": 12.238,
    "quantity_tonnes": null
  },
  {
    "reporter": 699,
    "partner": 400,
    "trade_value_usd_thousands": 12.628,
    "quantity_tonnes": null
  },
  {
    "reporter": 699,
    "partner": 458,
    "trade_value_usd_thousands": 11.447,
    "quantity_tonnes": null
  },
  {
    "reporter": 699,
    "partner": 470,
    "trade_value_usd_thousands": 0.027,
    "quantity_tonnes": null
  },
  {
    "reporter": 699,
    "partner": 512,
    "trade_value_usd_thousands": 1.782,
    "quantity_tonnes": null
  },
  {
    "reporter": 699,
    "partner": 646,
    "trade_value_usd_thousands": 450.366,
    "quantity_tonnes": null
  },
  {
    "reporter": 699,
    "partner": 682,
    "trade_value_usd_thousands": 709.971,
    "quantity_tonnes": null
  },
  {
    "reporter": 699,
    "partner": 724,
    "trade_value_usd_thousands": 3.453,
    "quantity_tonnes": 0.001
  },
  {
    "reporter": 699,
    "partner": 784,
    "trade_value_usd_thousands": 92.343,
    "quantity_tonnes": null
  },
  {
    "reporter": 699,
    "partner": 788,
    "trade_value_usd_thousands": 459.478,
    "quantity_tonnes": 0.004
  },
  {
    "reporter": 699,
    "partner": 818,
    "trade_value_usd_thousands": 759.078,
    "quantity_tonnes": null
  },
  {
    "reporter": 699,
    "partner": 842,
    "trade_value_usd_thousands": 377.367,
    "quantity_tonnes": null
  },
  {
    "reporter": 702,
    "partner": 124,
    "trade_value_usd_thousands": 41.433,
    "quantity_tonnes": null
  },
  {
    "reporter": 702,
    "partner": 208,
    "trade_value_usd_thousands": 40.261,
    "quantity_tonnes": null
  },
  {
    "reporter": 702,
    "partner": 344,
    "trade_value_usd_thousands": 459.684,
    "quantity_tonnes": null
  },
  {
    "reporter": 702,
    "partner": 392,
    "trade_value_usd_thousands": 9.181,
    "quantity_tonnes": null
  },
  {
    "reporter": 702,
    "partner": 458,
    "trade_value_usd_thousands": 126.191,
    "quantity_tonnes": null
  },
  {
    "reporter": 702,
    "partner": 699,
    "trade_value_usd_thousands": 405.539,
    "quantity_tonnes": 0.001
  },
  {
    "reporter": 702,
    "partner": 826,
    "trade_value_usd_thousands": 2.104,
    "quantity_tonnes": null
  },
  {
    "reporter": 702,
    "partner": 842,
    "trade_value_usd_thousands": 91.425,
    "quantity_tonnes": null
  },
  {
    "reporter": 703,
    "partner": 528,
    "trade_value_usd_thousands": 0.039,
    "quantity_tonnes": null
  },
  {
    "reporter": 704,
    "partner": 724,
    "trade_value_usd_thousands": 15.58,
    "quantity_tonnes": 0.001
  },
  {
    "reporter": 705,
    "partner": 528,
    "trade_value_usd_thousands": 0.439,
    "quantity_tonnes": null
  },
  {
    "reporter": 710,
    "partner": 40,
    "trade_value_usd_thousands": 49.415,
    "quantity_tonnes": null
  },
  {
    "reporter": 710,
    "partner": 56,
    "trade_value_usd_thousands": 40186.055,
    "quantity_tonnes": 0.11
  },
  {
    "reporter": 710,
    "partner": 72,
    "trade_value_usd_thousands": 998.25,
    "quantity_tonnes": 0.011
  },
  {
    "reporter": 710,
    "partner": 124,
    "trade_value_usd_thousands": 0.051,
    "quantity_tonnes": null
  },
  {
    "reporter": 710,
    "partner": 344,
    "trade_value_usd_thousands": 366.588,
    "quantity_tonnes": 0.001
  },
  {
    "reporter": 710,
    "partner": 372,
    "trade_value_usd_thousands": 34.208,
    "quantity_tonnes": 0.001
  },
  {
    "reporter": 710,
    "partner": 699,
    "trade_value_usd_thousands": 8691.785,
    "quantity_tonnes": 0.024
  },
  {
    "reporter": 710,
    "partner": 702,
    "trade_value_usd_thousands": 402.052,
    "quantity_tonnes": 0.001
  },
  {
    "reporter": 710,
    "partner": 784,
    "trade_value_usd_thousands": 169009.192,
    "quantity_tonnes": 0.383
  },
  {
    "reporter": 710,
    "partner": 826,
    "trade_value_usd_thousands": 795.476,
    "quantity_tonnes": 0.001
  },
  {
    "reporter": 710,
    "partner": 842,
    "trade_value_usd_thousands": 1.499,
    "quantity_tonnes": null
  },
  {
    "reporter": 716,
    "partner": 56,
    "trade_value_usd_thousands": 61666.117,
    "quantity_tonnes": 0.075
  },
  {
    "reporter": 716,
    "partner": 376,
    "trade_value_usd_thousands": 7325.0,
    "quantity_tonnes": null
  },
  {
    "reporter": 716,
    "partner": 699,
    "trade_value_usd_thousands": 2220.578,
    "quantity_tonnes": 0.005
  },
  {
    "reporter": 716,
    "partner": 784,
    "trade_value_usd_thousands": 66356.011,
    "quantity_tonnes": null
  },
  {
    "reporter": 724,
    "partner": 56,
    "trade_value_usd_thousands": 410.453,
    "quantity_tonnes": 0.001
  },
  {
    "reporter": 724,
    "partner": 251,
    "trade_value_usd_thousands": 5.024,
    "quantity_tonnes": 0.008
  },
  {
    "reporter": 724,
    "partner": 528,
    "trade_value_usd_thousands": 0.465,
    "quantity_tonnes": null
  },
  {
    "reporter": 724,
    "partner": 620,
    "trade_value_usd_thousands": 9.45,
    "quantity_tonnes": null
  },
  {
    "reporter": 752,
    "partner": 528,
    "trade_value_usd_thousands": 0.13,
    "quantity_tonnes": null
  },
  {
    "reporter": 757,
    "partner": 48,
    "trade_value_usd_thousands": 474.802,
    "quantity_tonnes": null
  },
  {
    "reporter": 757,
    "partner": 251,
    "trade_value_usd_thousands": 27.694,
    "quantity_tonnes": null
  },
  {
    "reporter": 757,
    "partner": 344,
    "trade_value_usd_thousands": 157.487,
    "quantity_tonnes": null
  },
  {
    "reporter": 757,
    "partner": 392,
    "trade_value_usd_thousands": 27.059,
    "quantity_tonnes": null
  },
  {
    "reporter": 764,
    "partner": 392,
    "trade_value_usd_thousands": 44.238,
    "quantity_tonnes": null
  },
  {
    "reporter": 784,
    "partner": 48,
    "trade_value_usd_thousands": 7.09,
    "quantity_tonnes": null
  },
  {
    "reporter": 784,
    "partner": 56,
    "trade_value_usd_thousands": 8654.425,
    "quantity_tonnes": 0.014
  },
  {
    "reporter": 784,
    "partner": 344,
    "trade_value_usd_thousands": 794.972,
    "quantity_tonnes": 0.002
  },
  {
    "reporter": 784,
    "partner": 376,
    "trade_value_usd_thousands": 15913.315,
    "quantity_tonnes": 0.032
  },
  {
    "reporter": 784,
    "partner": 458,
    "trade_value_usd_thousands": 0.124,
    "quantity_tonnes": null
  },
  {
    "reporter": 784,
    "partner": 699,
    "trade_value_usd_thousands": 5096.766,
    "quantity_tonnes": 0.025
  },
  {
    "reporter": 784,
    "partner": 710,
    "trade_value_usd_thousands": 22774.974,
    "quantity_tonnes": 0.046
  },
  {
    "reporter": 792,
    "partner": 826,
    "trade_value_usd_thousands": 4.022,
    "quantity_tonnes": 0.004
  },
  {
    "reporter": 826,
    "partner": 56,
    "trade_value_usd_thousands": 1.983,
    "quantity_tonnes": 0.001
  },
  {
    "reporter": 826,
    "partner": 124,
    "trade_value_usd_thousands": 1.831,
    "quantity_tonnes": 0.001
  },
  {
    "reporter": 826,
    "partner": 344,
    "trade_value_usd_thousands": 9.891,
    "quantity_tonnes": 0.002
  },
  {
    "reporter": 826,
    "partner": 360,
    "trade_value_usd_thousands": 0.881,
    "quantity_tonnes": 0.007
  },
  {
    "reporter": 826,
    "partner": 372,
    "trade_value_usd_thousands": 19.724,
    "quantity_tonnes": null
  },
  {
    "reporter": 826,
    "partner": 392,
    "trade_value_usd_thousands": 2.963,
    "quantity_tonnes": 0.001
  },
  {
    "reporter": 826,
    "partner": 528,
    "trade_value_usd_thousands": 0.021,
    "quantity_tonnes": null
  },
  {
    "reporter": 826,
    "partner": 554,
    "trade_value_usd_thousands": 0.246,
    "quantity_tonnes": null
  },
  {
    "reporter": 826,
    "partner": 784,
    "trade_value_usd_thousands": 3.798,
    "quantity_tonnes": 0.001
  },
  {
    "reporter": 834,
    "partner": 842,
    "trade_value_usd_thousands": 2.701,
    "quantity_tonnes": null
  },
  {
    "reporter": 842,
    "partner": 36,
    "trade_value_usd_thousands": 10.728,
    "quantity_tonnes": null
  },
  {
    "reporter": 842,
    "partner": 56,
    "trade_value_usd_thousands": 67.353,
    "quantity_tonnes": 0.001
  },
  {
    "reporter": 842,
    "partner": 188,
    "trade_value_usd_thousands": 3.715,
    "quantity_tonnes": 0.003
  },
  {
    "reporter": 842,
    "partner": 214,
    "trade_value_usd_thousands": 1116.063,
    "quantity_tonnes": 0.255
  },
  {
    "reporter": 842,
    "partner": 320,
    "trade_value_usd_thousands": 65.588,
    "quantity_tonnes": 0.132
  },
  {
    "reporter": 842,
    "partner": 372,
    "trade_value_usd_thousands": 0.097,
    "quantity_tonnes": null
  },
  {
    "reporter": 842,
    "partner": 458,
    "trade_value_usd_thousands": 0.139,
    "quantity_tonnes": null
  },
  {
    "reporter": 842,
    "partner": 579,
    "trade_value_usd_thousands": 9.699,
    "quantity_tonnes": 0.001
  },
  {
    "reporter": 842,
    "partner": 634,
    "trade_value_usd_thousands": 13.8,
    "quantity_tonnes": null
  },
  {
    "reporter": 842,
    "partner": 682,
    "trade_value_usd_thousands": 2.633,
    "quantity_tonnes": null
  },
  {
    "reporter": 842,
    "partner": 702,
    "trade_value_usd_thousands": 49.085,
    "quantity_tonnes": null
  },
  {
    "reporter": 842,
    "partner": 710,
    "trade_value_usd_thousands": 6.426,
    "quantity_tonnes": null
  },
  {
    "reporter": 842,
    "partner": 752,
    "trade_value_usd_thousands": 2.545,
    "quantity_tonnes": null
  },
  {
    "reporter": 842,
    "partner": 784,
    "trade_value_usd_thousands": 97.558,
    "quantity_tonnes": 0.001
  },
  {
    "reporter": 842,
    "partner": 826,
    "trade_value_usd_thousands": 34.634,
    "quantity_tonnes": null
  }
]